daman/__init__.py
daman/data_manager.py
daman/utils.py
daman/commands/__init__.py
daman/commands/aws.py
daman/commands/clear.py
daman/commands/configure.py
daman/commands/delete.py
daman/commands/download.py
daman/commands/summary.py
daman/configure/__init__.py
daman/configure/aws.py
daman/data/__init__.py
daman/data/registery.py
daman/services/__init__.py
daman/services/aws.py
daman/services/base.py
daman-0.2.0.dist-info/LICENSE
daman-0.2.0.dist-info/METADATA
daman-0.2.0.dist-info/WHEEL
daman-0.2.0.dist-info/entry_points.txt
daman-0.2.0.dist-info/top_level.txt
daman-0.2.0.dist-info/RECORD
