Metadata-Version: 2.1
Name: daman
Version: 0.2.0
Summary: A simple package that allows for the direct use of data stored and managed on a cloud storage service
Home-page: https://github.com/sofiane87/daman
Author: Sofiane Mahiou
Author-email: mahiou.sofiane@gmail.com
License: UNKNOWN
Project-URL: Bug Tracker, https://github.com/sofiane87/daman/issues
Platform: UNKNOWN
Classifier: Programming Language :: Python :: 3
Classifier: License :: OSI Approved :: MIT License
Classifier: Operating System :: OS Independent
Requires-Python: >=3.6.0
Requires-Dist: boto3 (==1.17.21)
Requires-Dist: orjson (==3.5.1)
Requires-Dist: psutil (==5.8.0)
Requires-Dist: tqdm (==4.59.0)
Requires-Dist: pandas (==1.2.3)
